dash_rangelineplot/Rangelineplot.py
dash_rangelineplot/__init__.py
dash_rangelineplot/_imports_.py
dash_rangelineplot/dash_rangelineplot.min.js
dash_rangelineplot/dash_rangelineplot.min.js.map
dash_rangelineplot/metadata.json
dash_rangelineplot/package-info.json
dash_rangelineplot-0.0.4.dist-info/LICENSE
dash_rangelineplot-0.0.4.dist-info/METADATA
dash_rangelineplot-0.0.4.dist-info/WHEEL
dash_rangelineplot-0.0.4.dist-info/top_level.txt
dash_rangelineplot-0.0.4.dist-info/RECORD
