Metadata-Version: 2.2
Name: dash_rangelineplot
Version: 0.0.4
Summary: A custom Dash component for interactive line plots with draggable range selectors, ideal for data filtering.
Home-page: https://github.com/gramos93/dash-rangelineplot
Author: Gabriel Ramos <piscina.ramos@gmail.com>
License: MIT
Project-URL: Bug Tracker, https://github.com/gramos93/dash-rangelineplot/issues
Project-URL: Documentation, https://github.com/gramos93/dash-rangelineplot#readme
Project-URL: Source Code, https://github.com/gramos93/dash-rangelineplot
Classifier: Framework :: Dash
License-File: LICENSE
Requires-Dist: dash
Requires-Dist: plotly
Dynamic: author
Dynamic: classifier
Dynamic: description
Dynamic: description-content-type
Dynamic: home-page
Dynamic: license
Dynamic: project-url
Dynamic: requires-dist
Dynamic: summary
